{
    "inventories": {
        "0": {
            "00": "LEER",
            "01": "LEER",
            "02": "LEER"
        },
        "1": {
            "00": "LEER",
            "01": "LEER",
            "02": "LEER",
            "03": "LEER",
            "04": "LEER"
        },
        "2": {
            "00": "LEER",
            "01": "LEER",
            "02": "LEER"
        },
        "3": {
            "00": "LEER",
            "01": "LEER",
            "02": "LEER",
            "03": "LEER",
            "04": "LEER",
            "05": "LEER",
            "06": "LEER",
            "07": "LEER",
            "08": "LEER",
            "09": "LEER",
            "10": "LEER",
            "11": "LEER",
            "12": "LEER",
            "13": "LEER",
            "14": "LEER",
            "15": "LEER",
            "16": "LEER",
            "17": "LEER",
            "18": "LEER",
            "19": "LEER"
        }
    },
    "playerInventory": {
        "0": "COLA",
        "1": "PIZZA",
        "2": "LEER",
        "3": "LEER",
        "4": "LEER"
    },
    "points": 0,
    "position": {
        "x": 343.8907470703125,
        "y": 378.8907470703125
    }
}